nak/__init__.py
nak/command.py
nak/config.py
nak/gateway.py
nak/nak.py
nak/parser.py
nak/settings.py
nak/utils.py
tests/__init__.py
tests/test_command.py
tests/test_conf.py
tests/test_gateway.py
tests/test_utils.py
test_tnn_app_kit-1.0.2.dist-info/LICENSE
test_tnn_app_kit-1.0.2.dist-info/METADATA
test_tnn_app_kit-1.0.2.dist-info/WHEEL
test_tnn_app_kit-1.0.2.dist-info/entry_points.txt
test_tnn_app_kit-1.0.2.dist-info/top_level.txt
test_tnn_app_kit-1.0.2.dist-info/RECORD
